aegis_core/__init__.py
aegis_core/ast/__init__.py
aegis_core/ast/features/__init__.py
aegis_core/ast/features/provider.py
aegis_core/ast/helpers.py
aegis_core/ast/metadata.py
aegis_core/indexing/__init__.py
aegis_core/indexing/project_index.py
aegis_core/reflection/__init__.py
aegis_core/registry.py
aegis_core/semantics.py
aegis_core-1.11.2.dist-info/WHEEL
aegis_core-1.11.2.dist-info/METADATA
aegis_core-1.11.2.dist-info/RECORD
