Metadata-Version: 2.4
Name: aegis-core
Version: 1.11.2
Summary: A library to manipulate Mecha for language server usage
Author: TheNuclearNexus
Author-email: TheNuclearNexus <39636175+TheNuclearNexus@users.noreply.github.com>
License-Expression: MIT
Classifier: Programming Language :: Python :: 3
Classifier: Programming Language :: Python :: 3.14
Requires-Dist: mecha>=0.102.0,<0.103
Requires-Dist: bolt>=0.50.0,<0.51
Requires-Dist: lsprotocol>=2023.0.1,<2024
Requires-Dist: numpy==2.4.1
Requires-Python: >=3.14
